Workbook

Sheet Devis
A1: MAUREL'EC | E1: DEVIS N° | F1: [à compléter]
A2: Électricité générale – Domotique | E2: Date | F2: 15/10/2026
A3: [Adresse] – [Téléphone] – maurelec.btp@gmail.com | E3: Validité | F3: 3 mois
A4: Entrepreneur individuel (micro-entreprise) – SIRET : [à compléter] – Assurance décennale : [à compléter]
A6: CLIENTE : | B6: Mme [Nom] – [Adresse du chantier]
A7: OBJET : | B7: Rénovation électrique complète d'un appartement T4 (97,57 m² + 2 balcons) – installation 100 % connectée Legrand Céliane with Netatmo, pilotable sur smartphone, conforme NF C 15-100. Premier chiffrage établi sur plan, sans visite.
A9: N° | B9: Désignation (fourniture et pose) | C9: Unité | D9: Qté | E9: PU | F9: Total
A10: 1 | B10: INSTALLATION DE CHANTIER ET DÉCHETS
A11: 1.1 | B11: Approvisionnement du chantier : livraison du matériel, protections sols/menuiseries, mise en sécurité de l'installation existante | C11: Forfait | D11: 1 | E11: 650 | F11: =D11*E11 -> 650
A12: 1.2 | B12: Débarrassage, tri, évacuation et mise en déchetterie des déchets (gravats de saignées, câbles, emballages), frais de déchetterie inclus | C12: Forfait | D12: 1 | E12: 850 | F12: =D12*E12 -> 850
E13: Sous-total lot 1 | F13: =SUM(F11:F12) -> 1500
A15: 2 | B15: SAIGNÉES ET ENCASTREMENT EN MURS DURS ET SOLS
A16: 2.1 | B16: Saignées en murs durs (béton / maçonnerie pleine) à la rainureuse avec aspiration | C16: ml | D16: 160 | E16: 30 | F16: =D16*E16 -> 4800
A17: 2.2 | B17: Saignées au sol (dalle / chape) pour passage des gaines ICTA | C17: ml | D17: 70 | E17: 26 | F17: =D17*E17 -> 1820
A18: 2.3 | B18: Carottage et scellement des boîtes d'encastrement Ø67 dans le béton | C18: U | D18: 140 | E18: 9 | F18: =D18*E18 -> 1260
A19: 2.4 | B19: Carottages de traversée de murs porteurs / cloisons béton | C19: U | D19: 10 | E19: 45 | F19: =D19*E19 -> 450
A20: 2.5 | B20: Rebouchage des saignées au mortier / enduit (prêt à peindre, hors peinture) | C20: ml | D20: 230 | E20: 7 | F20: =D20*E20 -> 1610
E21: Sous-total lot 2 | F21: =SUM(F16:F20) -> 9940
A23: 3 | B23: TABLEAU ÉLECTRIQUE ET GTL (situés dans le hall d'entrée)
A24: 3.1 | B24: GTL Legrand 13 modules (hauteur 2,60 m) avec couvercles | C24: U | D24: 1 | E24: 420 | F24: =D24*E24 -> 420
A25: 3.2 | B25: Coffret Legrand Drivia 18 modules 4 rangées avec porte (≈ 20 % de réserve) | C25: U | D25: 1 | E25: 460 | F25: =D25*E25 -> 460
A26: 3.3 | B26: Interrupteur différentiel Legrand 40 A 30 mA type A (circuits éclairage, prises, équipements) | C26: U | D26: 3 | E26: 175 | F26: =D26*E26 -> 525
A27: 3.4 | B27: Interrupteur différentiel Legrand 40 A 30 mA type F (cuisson, lave-linge, climatisations) | C27: U | D27: 1 | E27: 260 | F27: =D27*E27 -> 260
A28: 3.5 | B28: Interrupteur différentiel Legrand 63 A 30 mA type A (circuits plancher chauffant) | C28: U | D28: 2 | E28: 210 | F28: =D28*E28 -> 420
A29: 3.6 | B29: Disjoncteur Legrand DX3 Ph+N 2 A (filtre à air / ventilation) | C29: U | D29: 1 | E29: 38 | F29: =D29*E29 -> 38
A30: 3.7 | B30: Disjoncteur Legrand DX3 Ph+N 10 A (circuits éclairage) | C30: U | D30: 4 | E30: 38 | F30: =D30*E30 -> 152
A31: 3.8 | B31: Disjoncteur Legrand DX3 Ph+N 16 A (prises, volets, stores, porte WC, filtre à eau, balcons, alarme/caméras, coffret com., hotte) | C31: U | D31: 11 | E31: 38 | F31: =D31*E31 -> 418
A32: 3.9 | B32: Disjoncteur Legrand DX3 Ph+N 16 A (circuits plancher chauffant, 1 par zone) | C32: U | D32: 9 | E32: 38 | F32: =D32*E32 -> 342
A33: 3.10 | B33: Disjoncteur Legrand DX3 Ph+N 20 A (prises séjour/cuisine, four, lave-vaisselle, lave-linge, sèche-linge, congélateur, chauffe-eau, 4 climatisations) | C33: U | D33: 12 | E33: 42 | F33: =D33*E33 -> 504
A34: 3.11 | B34: Disjoncteur Legrand DX3 Ph+N 32 A (plaque de cuisson) | C34: U | D34: 1 | E34: 48 | F34: =D34*E34 -> 48
A35: 3.12 | B35: Contacteur jour/nuit Legrand 20 A (chauffe-eau, heures creuses) | C35: U | D35: 1 | E35: 95 | F35: =D35*E35 -> 95
A36: 3.13 | B36: Parafoudre Legrand type 2 Ph+N avec disjoncteur de déconnexion associé | C36: U | D36: 1 | E36: 340 | F36: =D36*E36 -> 340
A37: 3.14 | B37: Drivia with Netatmo : pack module Control + contacteur connecté (412191B) + module de mesure (412015) | C37: U | D37: 1 | E37: =ROUND('Références fournisseur'!$I$7*1+'Références fournisseur'!$I$8*1+35,2) -> 439.31 | F37: =D37*E37 -> 439.31
A38: 3.15 | B38: Peignes, borniers, repérage des circuits, câblage et mise en ordre du tableau | C38: Forfait | D38: 1 | E38: 480 | F38: =D38*E38 -> 480
A39: 3.16 | B39: Tableau de communication Legrand Drivia grade 3TV (DTI, répartiteur RJ45, prise de courant intégrée) | C39: U | D39: 1 | E39: 680 | F39: =D39*E39 -> 680
A40: 3.17 | B40: Mise à la terre : barrette de coupure, conducteur principal, liaisons équipotentielles | C40: Forfait | D40: 1 | E40: 290 | F40: =D40*E40 -> 290
E41: Sous-total lot 3 | F41: =SUM(F24:F40) -> 5911.31
A43: 4 | B43: CRÉATION DES CIRCUITS DEPUIS LE TABLEAU (câble + gaine ICTA du tableau jusqu'au 1er point, raccordement au tableau)
A44: 4.1 | B44: Circuits éclairage : zone jour, zone nuit, pièces d'eau/WC/buanderie, balcons | C44: Circuit | D44: 4 | E44: 190 | F44: =D44*E44 -> 760
A45: 4.2 | B45: Circuits prises : séjour, chambres 1-2, chambre 3/hall/dégagement, salles de bain, cuisine, balcons (+ brumisateurs/ventilateurs) | C45: Circuit | D45: 6 | E45: 190 | F45: =D45*E45 -> 1140
A46: 4.3 | B46: Circuits volets roulants et stores | C46: Circuit | D46: 2 | E46: 190 | F46: =D46*E46 -> 380
A47: 4.4 | B47: Circuits spécialisés : plaque, four, lave-vaisselle, hotte, lave-linge, sèche-linge, congélateur, chauffe-eau, filtre à eau, filtre à air, porte WC | C47: Circuit | D47: 11 | E47: 190 | F47: =D47*E47 -> 2090
A48: 4.5 | B48: Circuits alarme/caméras et coffret de communication | C48: Circuit | D48: 2 | E48: 190 | F48: =D48*E48 -> 380
A49: 4.6 | B49: Circuits climatisations réversibles (jusqu'aux unités extérieures) | C49: Circuit | D49: 4 | E49: 190 | F49: =D49*E49 -> 760
A50: 4.7 | B50: Circuits plancher chauffant (1 par zone) | C50: Circuit | D50: 9 | E50: 190 | F50: =D50*E50 -> 1710
E51: Sous-total lot 4 | F51: =SUM(F44:F50) -> 7220
A53: 5 | B53: ÉCLAIRAGE CONNECTÉ – LEGRAND CÉLIANE WITH NETATMO
A54: 5.1 | B54: Point lumineux plafond DCL (boîte DCL + douille + fiche), dérivation 1,5 mm² sous ICTA sur le circuit éclairage – séjour 3, cuisine 2, chambres 3, SDB 4, WC 1, hall 1, dégagement 2, buanderie 1, dressing 1 | C54: U | D54: 18 | E54: 70 | F54: =D54*E54 -> 1260
A55: 5.2 | B55: Création des liaisons de commande (câble 1,5 mm² sous ICTA, boîte d'encastrement) – interrupteurs des pièces 14 + bibliothèque 1 | C55: U | D55: 15 | E55: 45 | F55: =D55*E55 -> 675
A56: 5.3 | B56: Interrupteur connecté Céliane with Netatmo avec neutre CB0409 + plaque – fourniture et pose – séjour 2, cuisine 2, chambres 3, SDB 2, WC 1, hall 1, dégagement 1, buanderie 1, dressing 1 | C56: U | D56: 14 | E56: =ROUND('Références fournisseur'!$I$11*1+'Références fournisseur'!$I$27*1+35,2) -> 114.87 | F56: =D56*E56 -> 1608.18
A57: 5.4 | B57: Bibliothèque du séjour : alimentation éclairage en attente (dérivation, boîte de raccordement, emplacement à définir) | C57: U | D57: 1 | E57: 55 | F57: =D57*E57 -> 55
A58: 5.5 | B58: Bibliothèque du séjour : variateur connecté Céliane with Netatmo CB0409 + plaque – fourniture et pose | C58: U | D58: 1 | E58: =ROUND('Références fournisseur'!$I$11*1+'Références fournisseur'!$I$27*1+35,2) -> 114.87 | F58: =D58*E58 -> 114.87
A59: 5.6 | B59: Commande sans fil Self-e Céliane with Netatmo CB0420 + plaque (têtes de lit 3, séjour 1, dégagement 1) – fourniture et pose | C59: U | D59: 5 | E59: =ROUND('Références fournisseur'!$I$12*1+'Références fournisseur'!$I$27*1+35,2) -> 122.39 | F59: =D59*E59 -> 611.95
A60: 5.7 | B60: Commande générale sans fil « Départ / Arrivée » CB0400 + plaque (entrée) – fourniture et pose | C60: U | D60: 1 | E60: =ROUND('Références fournisseur'!$I$13*1+'Références fournisseur'!$I$27*1+35,2) -> 75.53 | F60: =D60*E60 -> 75.53
A61: 5.8 | B61: Commande sans fil « Lever / Coucher » CB0423 + plaque (chambre parentale) – fourniture et pose | C61: U | D61: 1 | E61: =ROUND('Références fournisseur'!$I$14*1+'Références fournisseur'!$I$27*1+35,2) -> 84.39 | F61: =D61*E61 -> 84.39
E62: Sous-total lot 5 | F62: =SUM(F54:F61) -> 4484.92
A64: 6 | B64: PRISES DE COURANT ET COMMUNICATION (NF C 15-100)
A65: 6.1 | B65: Dérivation des points prises 16 A sur leur circuit (câble 2,5 mm², gaine ICTA, boîte d'encastrement) – 21 standard + 5 connectées | C65: U | D65: 26 | E65: 45 | F65: =D65*E65 -> 1170
A66: 6.2 | B66: Prise de courant 16 A 2P+T Céliane (CM0111 + CB0111 + support + plaque) – fourniture et pose – minimum NF C 15-100 : séjour 5, chambres 2 x3, cuisine 6 (dont 4 plan de travail, frigo), SDB 1 x2, hall 1, dégagement 1 | C66: U | D66: 21 | E66: =ROUND('Références fournisseur'!$I$20*1+'Références fournisseur'!$I$21*1+'Références fournisseur'!$I$22*1+'Références fournisseur'!$I$27*1+35,2) -> 44.28 | F66: =D66*E66 -> 929.88
A67: 6.3 | B67: Prise de courant connectée Céliane with Netatmo CB0460 + plaque (pilotage + mesure) – séjour 2, chambres 3 – fourniture et pose | C67: U | D67: 5 | E67: =ROUND('Références fournisseur'!$I$19*1+'Références fournisseur'!$I$27*1+35,2) -> 106.68 | F67: =D67*E67 -> 533.4
A68: 6.4 | B68: Création des lignes RJ45 cat. 6A depuis le tableau de communication (câble, gaine, boîte) | C68: U | D68: 5 | E68: 65 | F68: =D68*E68 -> 325
A69: 6.5 | B69: Prise RJ45 grade 3TV Céliane (CM0346 + CB0346 + support + plaque) – séjour 2, chambres 3 – fourniture et pose | C69: U | D69: 5 | E69: =ROUND('Références fournisseur'!$I$23*1+'Références fournisseur'!$I$24*1+'Références fournisseur'!$I$22*1+'Références fournisseur'!$I$27*1+35,2) -> 63.84 | F69: =D69*E69 -> 319.2
E70: Sous-total lot 6 | F70: =SUM(F65:F69) -> 3277.48
A72: 7 | B72: VOLETS ROULANTS ET STORES CONNECTÉS
A73: 7.1 | B73: Dérivation des alimentations moteurs sur le circuit volets/stores (câble, boîte de raccordement) – 6 volets + 2 stores | C73: U | D73: 8 | E73: 60 | F73: =D73*E73 -> 480
A74: 7.2 | B74: Interrupteur de volet roulant connecté Céliane with Netatmo CB0431 + plaque – chambres 3, séjour 2, cuisine 1 – fourniture et pose | C74: U | D74: 6 | E74: =ROUND('Références fournisseur'!$I$16*1+'Références fournisseur'!$I$27*1+35,2) -> 118.83 | F74: =D74*E74 -> 712.98
A75: 7.3 | B75: Interrupteur de store connecté Céliane with Netatmo CB0431 + plaque (stores des balcons) – fourniture et pose | C75: U | D75: 2 | E75: =ROUND('Références fournisseur'!$I$16*1+'Références fournisseur'!$I$27*1+35,2) -> 118.83 | F75: =D75*E75 -> 237.66
A76: 7.4 | B76: Commande générale volets roulants sans fil Céliane with Netatmo CB0432 + plaque – fourniture et pose | C76: U | D76: 1 | E76: =ROUND('Références fournisseur'!$I$17*1+'Références fournisseur'!$I$27*1+35,2) -> 118.87 | F76: =D76*E76 -> 118.87
E77: Sous-total lot 7 | F77: =SUM(F73:F76) -> 1549.51
A79: 8 | B79: CHAUFFAGE AU SOL – ALIMENTATIONS EN ATTENTE
A80: 8.1 | B80: Attente par zone de plancher chauffant : boîte de raccordement en fin de circuit – séjour, 3 chambres, cuisine, 2 SDB, hall/dégagement, buanderie/dressing (trame et thermostat non fournis) | C80: U | D80: 9 | E80: 45 | F80: =D80*E80 -> 405
E81: Sous-total lot 8 | F81: =SUM(F80:F80) -> 405
A83: 9 | B83: CLIMATISATIONS RÉVERSIBLES (alimentations)
A84: 9.1 | B84: Attente climatisation à côté de l'unité extérieure, en fin de circuit 20 A (raccordement direct sur le groupe par le climaticien) | C84: U | D84: 4 | E84: 45 | F84: =D84*E84 -> 180
E85: Sous-total lot 9 | F85: =SUM(F84:F84) -> 180
A87: 10 | B87: CUISINE, ÉLECTROMÉNAGER ET ÉQUIPEMENTS (alimentations)
A88: 10.1 | B88: Sortie de câble 32 A plaque de cuisson – fourniture et pose | C88: U | D88: 1 | E88: 60 | F88: =D88*E88 -> 60
A89: 10.2 | B89: Prise spécialisée 20 A four – fourniture et pose | C89: U | D89: 1 | E89: 195 | F89: =D89*E89 -> 195
A90: 10.3 | B90: Prise spécialisée 20 A lave-vaisselle – fourniture et pose | C90: U | D90: 1 | E90: 195 | F90: =D90*E90 -> 195
A91: 10.4 | B91: Sortie de câble hotte – fourniture et pose | C91: U | D91: 1 | E91: 45 | F91: =D91*E91 -> 45
A92: 10.5 | B92: Buanderie – prise spécialisée 20 A lave-linge – fourniture et pose | C92: U | D92: 1 | E92: 195 | F92: =D92*E92 -> 195
A93: 10.6 | B93: Buanderie – prise spécialisée 20 A sèche-linge – fourniture et pose | C93: U | D93: 1 | E93: 195 | F93: =D93*E93 -> 195
A94: 10.7 | B94: Buanderie – prise spécialisée 20 A congélateur – fourniture et pose | C94: U | D94: 1 | E94: 195 | F94: =D94*E94 -> 195
A95: 10.8 | B95: Buanderie – sortie de câble chauffe-eau (circuit via contacteur jour/nuit) – fourniture et pose | C95: U | D95: 1 | E95: 45 | F95: =D95*E95 -> 45
A96: 10.9 | B96: Prise dédiée filtre à eau sous évier – fourniture et pose | C96: U | D96: 1 | E96: 195 | F96: =D96*E96 -> 195
A97: 10.10 | B97: Sortie de câble filtre à air – fourniture et pose | C97: U | D97: 1 | E97: 45 | F97: =D97*E97 -> 45
A98: 10.11 | B98: Commande connectée filtre à air Céliane with Netatmo CB0409 + plaque – fourniture et pose | C98: U | D98: 1 | E98: =ROUND('Références fournisseur'!$I$11*1+'Références fournisseur'!$I$27*1+35,2) -> 114.87 | F98: =D98*E98 -> 114.87
A99: 10.12 | B99: Sortie de câble porte électrique WC – fourniture et pose (porte non fournie) | C99: U | D99: 1 | E99: 45 | F99: =D99*E99 -> 45
E100: Sous-total lot 10 | F100: =SUM(F88:F99) -> 1524.87
A102: 11 | B102: BALCONS (2)
A103: 11.1 | B103: Attente éclairage extérieur (dérivation, boîte étanche) – balcon séjour 2, balcon chambre/cuisine 1 – appliques non fournies | C103: U | D103: 3 | E103: 55 | F103: =D103*E103 -> 165
A104: 11.2 | B104: Création des liaisons de commande éclairage balcons (câble, gaine, boîte) | C104: U | D104: 2 | E104: 45 | F104: =D104*E104 -> 90
A105: 11.3 | B105: Interrupteur connecté Céliane with Netatmo CB0409 + plaque pour éclairage balcon – fourniture et pose | C105: U | D105: 2 | E105: =ROUND('Références fournisseur'!$I$11*1+'Références fournisseur'!$I$27*1+35,2) -> 114.87 | F105: =D105*E105 -> 229.74
A106: 11.4 | B106: Attente brumisateurs et ventilateurs (dérivation, boîte étanche, liaison de commande) – 1 brumisateur + 1 ventilateur par balcon | C106: U | D106: 4 | E106: 55 | F106: =D106*E106 -> 220
A107: 11.5 | B107: Commande connectée brumisateur / ventilateur Céliane with Netatmo CB0409 + plaque – fourniture et pose | C107: U | D107: 4 | E107: =ROUND('Références fournisseur'!$I$11*1+'Références fournisseur'!$I$27*1+35,2) -> 114.87 | F107: =D107*E107 -> 459.48
A108: 11.6 | B108: Dérivation des points prises extérieures (câble 2,5 mm², gaine, boîte étanche) | C108: U | D108: 2 | E108: 45 | F108: =D108*E108 -> 90
A109: 11.7 | B109: Prise de courant étanche Legrand Plexo IP55 (069551L + 069651L) – 1 par balcon – fourniture et pose | C109: U | D109: 2 | E109: =ROUND('Références fournisseur'!$I$25*1+'Références fournisseur'!$I$26*1+35,2) -> 46.65 | F109: =D109*E109 -> 93.3
E110: Sous-total lot 11 | F110: =SUM(F103:F109) -> 1347.52
A112: 12 | B112: SÉCURITÉ : DÉTECTION, ALARME, CAMÉRAS
A113: 12.1 | B113: Détecteur de fumée connecté Netatmo NSA-PRO-FR NF EN 14604 – hall, dégagement nuit, séjour – fourniture et pose | C113: U | D113: 3 | E113: =ROUND('Références fournisseur'!$I$29*1+35,2) -> 175.46 | F113: =D113*E113 -> 526.38
...

Sheet Références fournisseur
A1: Références Legrand / Netatmo à chiffrer chez le fournisseur
A2: Prix d'achat HT Rexel en colonne F (cellules jaunes) – les prix de vente du devis en découlent (× coefficient F3 + pose 35 €). « Vérifié » = référence lue sur legrand.fr (oct. 2026) ; « À confirmer » = à valider avec le fournisseur (gamme en cours de renouvellement). Tarif public = indicatif.
E3: Coefficient de marge | F3: 1.4
A4: Désignation | B4: Réf. Legrand | C4: Usage dans le devis | D4: Qté | E4: Tarif public HT (info) | F4: Ton prix achat HT | G4: Total achat HT | H4: Statut
A5: Désignation | B5: Réf. Legrand | C5: Usage dans le devis | D5: Qté | E5: Tarif public HT (info) | F5: Ton prix achat HT | G5: Total achat HT | H5: Statut | I5: Prix vente HT (achat × coef)
A6: PASSERELLE ET TABLEAU CONNECTÉ
A7: Pack de démarrage Drivia with Netatmo : module Control + contacteur connecté | B7: 412191B | C7: Passerelle de toute l'installation (au tableau) + pilotage du cumulus | D7: 1 | E7: 297.2 | F7: 196.54 | G7: =D7*F7 -> 196.54 | H7: Vérifié | I7: =F7*$F$3 -> 275.156
A8: Module de mesure de consommation connecté Drivia with Netatmo | B8: 412015 | C8: Suivi des consommations au tableau | D8: 1 | F8: 92.25 | G8: =D8*F8 -> 92.25 | H8: À confirmer | I8: =F8*$F$3 -> 129.15
A9: (Alternative) Pack de démarrage Céliane with Netatmo : prise Control + commande Départ/Arrivée, blanc | B9: CB0443 | C9: Seulement si on ne prend pas la passerelle Drivia | D9: 0 | E9: 144.1 | G9: =D9*F9 -> 0 | H9: Vérifié | I9: =F9*$F$3 -> 0
A10: ÉCLAIRAGE ET COMMANDES CONNECTÉES CÉLIANE WITH NETATMO
A11: Interrupteur filaire connecté avec neutre, option variation, avec support et enjoliveur blanc | B11: CB0409 | C11: Éclairage pièces (14), balcons (2), variateur bibliothèque (1), brumisateurs + ventilateurs (4), filtre à air (1) | D11: 22 | F11: 55.77 | G11: =D11*F11 -> 1226.94 | H11: Vérifié | I11: =F11*$F$3 -> 78.078
A12: Commande sans fils Self-e (sans pile) éclairage et prises, avec support et enjoliveur blanc | B12: CB0420 | C12: Va-et-vient : têtes de lit (3), séjour (1), dégagement (1) | D12: 5 | F12: 61.14 | G12: =D12*F12 -> 305.7 | H12: À confirmer | I12: =F12*$F$3 -> 85.596
A13: Commande générale sans fils Départ/Arrivée, avec support et enjoliveur blanc | B13: CB0400 | C13: Entrée | D13: 1 | F13: 27.67 | G13: =D13*F13 -> 27.67 | H13: À confirmer | I13: =F13*$F$3 -> 38.738
A14: Commande Lever/Coucher Self-e sans fils, sans pile, avec support et enjoliveur blanc | B14: CB0423 | C14: Chambre parentale (remplacée par 064884L à épuisement) | D14: 1 | E14: 91.24 | F14: 34 | G14: =D14*F14 -> 34 | H14: Vérifié | I14: =F14*$F$3 -> 47.6
A15: VOLETS ROULANTS ET STORES
A16: Interrupteur connecté pour volets roulants et stores, avec support et enjoliveur blanc | B16: CB0431 | C16: 6 volets + 2 stores (moteurs filaires obligatoires) | D16: 8 | F16: 58.6 | G16: =D16*F16 -> 468.8 | H16: Vérifié | I16: =F16*$F$3 -> 82.04
A17: Commande sans fils pour volets roulants, avec support et enjoliveur blanc | B17: CB0432 | C17: Commande générale des volets | D17: 1 | F17: 58.63 | G17: =D17*F17 -> 58.63 | H17: Vérifié | I17: =F17*$F$3 -> 82.082
A18: PRISES
A19: Prise connectée 16 A Céliane with Netatmo avec support et enjoliveur blanc (mesure conso) | B19: CB0460 | C19: Séjour (2), chambres (3) | D19: 5 | E19: 76.8 | F19: 49.92 | G19: =D19*F19 -> 249.6 | H19: Vérifié | I19: =F19*$F$3 -> 69.888
A20: Prise 2P+T Céliane bornes automatiques (mécanisme) | B20: CM0111 | C20: Prises standard | D20: 21 | F20: 3 | G20: =D20*F20 -> 63 | H20: À confirmer | I20: =F20*$F$3 -> 4.2
A21: Enjoliveur prise 2P+T Surface Confort Céliane blanc | B21: CB0111 | C21: Prises standard | D21: 21 | F21: 0.84 | G21: =D21*F21 -> 17.64 | H21: Vérifié | I21: =F21*$F$3 -> 1.176
A22: Support Céliane 1 poste (pour mécanismes CM) | B22: à confirmer | C22: Prises standard + RJ45 | D22: 26 | F22: 1.51 | G22: =D22*F22 -> 39.26 | H22: À confirmer | I22: =F22*$F$3 -> 2.114
A23: Prise RJ45 Céliane cat. 6A STP grade 3TV (mécanisme) | B23: CM0346 | C23: Séjour (2), chambres (3) | D23: 5 | E23: 24.51 | F23: 15.47 | G23: =D23*F23 -> 77.35 | H23: Vérifié | I23: =F23*$F$3 -> 21.658
A24: Enjoliveur RJ45 grade 3TV Céliane blanc | B24: CB0346 | C24: Séjour (2), chambres (3) | D24: 5 | E24: 4.76 | F24: 2.34 | G24: =D24*F24 -> 11.7 | H24: Vérifié | I24: =F24*$F$3 -> 3.276
A25: Prise 2P+T Plexo étanche IP55 gris à composer | B25: 069551L | C25: Balcons | D25: 2 | F25: 6.32 | G25: =D25*F25 -> 12.64 | H25: À confirmer | I25: =F25*$F$3 -> 8.848
A26: Boîtier saillie Plexo 1 poste (ou support encastré 069681L) | B26: 069651L | C26: Balcons | D26: 2 | F26: 2 | G26: =D26*F26 -> 4 | H26: À confirmer | I26: =F26*$F$3 -> 2.8
A27: Plaque de finition Céliane 1 poste (finition au choix de la cliente) | B27: selon finition | C27: 1 par appareil Céliane (67) | D27: 67 | F27: 1.28 | G27: =D27*F27 -> 85.76 | H27: À confirmer | I27: =F27*$F$3 -> 1.792
A28: SÉCURITÉ NETATMO
A29: Détecteur de fumée intelligent Netatmo (pile 10 ans) | B29: NSA-PRO-FR | C29: Hall, dégagement, séjour | D29: 3 | E29: 161.5 | F29: 100.33 | G29: =D29*F29 -> 300.99 | H29: Vérifié | I29: =F29*$F$3 -> 140.462
A30: Caméra intérieure intelligente Netatmo (centrale de l'alarme) | B30: NSC-PRO | C30: Hall d'entrée – pas de prix Rexel, prix devis estimé | D30: 1 | G30: =D30*F30 -> 0 | H30: À confirmer | I30: =F30*$F$3 -> 0
A31: Sirène intérieure intelligente Netatmo | B31: NIS01-PRO | C31: Hall | D31: 1 | F31: 79.41 | G31: =D31*F31 -> 79.41 | H31: À confirmer | I31: =F31*$F$3 -> 111.174
A32: Caméra extérieure intelligente Netatmo (NOC-S-PRO = avec sirène) | B32: NOC-PRO | C32: Balcons – pas de prix Rexel, prix devis estimé | D32: 2 | G32: =D32*F32 -> 0 | H32: À confirmer | I32: =F32*$F$3 -> 0
F34: Total achat HT | G34: =SUM(G6:G32) -> 3351.88
A36: Tableau électrique (coffret Drivia 4 rangées, GTL 13 modules, 6 interrupteurs différentiels, 38 disjoncteurs DX3, parafoudre, contacteur jour/nuit, tableau de communication grade 3TV) : à chiffrer par le fournisseur sur la liste de l'onglet « Tableau électrique ».

Sheet Tableau électrique
A1: Répartition prévisionnelle des circuits – coffret Drivia 4 rangées (hall d'entrée)
A2: En tête : disjoncteur de branchement Enedis, parafoudre type 2, module Control Drivia with Netatmo + mesure.
A4: N° | B4: Différentiel 30 mA | C4: Circuit | D4: Disjoncteur | E4: Section
A5: 1 | B5: ID1 – 40 A type A | C5: Éclairage zone jour (séjour, bibliothèque, cuisine, hall) | D5: 10 A | E5: 1,5 mm²
A6: 2 | B6: ID1 – 40 A type A | C6: Éclairage zone nuit (chambres, dégagement, dressing) | D6: 10 A | E6: 1,5 mm²
A7: 3 | B7: ID1 – 40 A type A | C7: Prises séjour (7) | D7: 20 A | E7: 2,5 mm²
A8: 4 | B8: ID1 – 40 A type A | C8: Prises chambres 1 et 2 (6) | D8: 16 A | E8: 2,5 mm²
A9: 5 | B9: ID1 – 40 A type A | C9: Volets roulants (6) | D9: 16 A | E9: 1,5 mm²
A10: 6 | B10: ID1 – 40 A type A | C10: Stores balcons (2) | D10: 16 A | E10: 1,5 mm²
A11: 7 | B11: ID1 – 40 A type A | C11: Coffret de communication | D11: 16 A | E11: 1,5 mm²
A12: 8 | B12: ID1 – 40 A type A | C12: Filtre à air | D12: 2 A | E12: 1,5 mm²
A13: 9 | B13: ID2 – 40 A type A | C13: Éclairage SDB 1, SDB 2, WC, buanderie | D13: 10 A | E13: 1,5 mm²
A14: 10 | B14: ID2 – 40 A type A | C14: Éclairage balcons (extérieur) | D14: 10 A | E14: 1,5 mm²
A15: 11 | B15: ID2 – 40 A type A | C15: Prises chambre 3, hall, dégagement (5) | D15: 16 A | E15: 2,5 mm²
A16: 12 | B16: ID2 – 40 A type A | C16: Prises SDB 1, SDB 2 (2) | D16: 16 A | E16: 2,5 mm²
... A42: 38 | B42: ID6 – 63 A type A | C42: Plancher chauffant salle de bain 2 | D42: 16 A | E42: 2,5 mm²
C44: Nombre de circuits | D44: =COUNTA(C5:C42) -> 38
C45: Nombre maximum de circuits par différentiel (8 recommandé) | D45: =MAX(COUNTIF(B5:B42,"ID1*"),COUNTIF(B5:B42,"ID2*"),COUNTIF(B5:B42,"ID3*"),COUNTIF(B5:B42,"ID4*"),COUNTIF(B5:B42,"ID5*"),COUNTIF(B5:B42,"ID6*")) -> 8

Sheet Points à vérifier
B1: Hypothèses retenues et points à vérifier lors de la visite
A3: • | B3: SANS CONTACT : à valider avec la cliente. Devis établi avec des interrupteurs connectés Céliane with Netatmo partout (pas de tactile dans cette gamme) ; le sans contact passe par la voix et le smartphone.
A4: • | B4: PUISSANCE : plancher chauffant (~8,5 kW) + 4 climatisations + cuisson → vérifier l'abonnement (probablement 18 kVA mono ou passage en triphasé). Délesteur conseillé (en option).
A5: • | B5: PLANCHER CHAUFFANT ÉLECTRIQUE : alimentations en attente uniquement. Trames et thermostats fournis et posés par le fournisseur du plancher (prévoir leurs thermostats compatibles smartphone si la cliente veut tout piloter).
A6: • | B6: BUANDERIE : lave-linge, sèche-linge, congélateur et chauffe-eau. Vérifier la place (2,56 m² sur le plan) et le passage des câbles.
A7: • | B7: BIBLIOTHÈQUE DU SÉJOUR : emplacement à définir ; alimentation + variateur connecté prévus, spots (variante A) ou ruban LED (variante B) en option.
A8: • | B8: VOLETS : 6 estimés d'après le plan (3 chambres, 2 séjour, 1 cuisine). STORES : 2 estimés (balcons). À compter sur place.
A9: • | B9: CAMÉRAS : 3 points d'alimentation + 2 caméras extérieures fournies – à confirmer avec la cliente (ou alimentation seule).
A10: • | B10: PIÈCES : la cliente annonce 3 chambres, séjour, cuisine, buanderie, dressing, 2 SDB, WC. Les « SÉCH. » / « RANGT. » du plan sont supposés être la buanderie et le dressing.
A11: • | B11: PRISES : nombre minimum NF C 15-100 (séjour 7, chambres 3, cuisine 6, SDB 1, hall et dégagement 1). Dressing, buanderie et WC < 4 m² : pas de prise imposée. Balcons : 1 prise étanche par balcon (demande client).
A12: • | B12: Saignées : 160 ml murs + 70 ml sol estimés pour un immeuble béton – à recaler à la visite (ce poste pèse lourd dans le total).
A13: • | B13: PRIX : appareillage connecté et Netatmo = prix d'achat Rexel × 1,40 + pose 35 € par appareil ; création des circuits depuis le tableau = 190 € par circuit (38 circuits), dérivations vers les points comptées à part. Caméras NSC-PRO / NOC-PRO : pas de prix Rexel, prix estimés.
B15: Légende : chiffres en BLEU = quantités / prix modifiables. Montants sans TVA (micro-entreprise, art. 293 B du CGI).
